odoo/addons/stock_request_kanban/README.rst
odoo/addons/stock_request_kanban/__init__.py
odoo/addons/stock_request_kanban/__manifest__.py
odoo/addons/stock_request_kanban/data/stock_request_sequence_data.xml
odoo/addons/stock_request_kanban/i18n/es.po
odoo/addons/stock_request_kanban/i18n/stock_request_kanban.pot
odoo/addons/stock_request_kanban/i18n/zh_CN.po
odoo/addons/stock_request_kanban/models/__init__.py
odoo/addons/stock_request_kanban/models/product.py
odoo/addons/stock_request_kanban/models/stock_inventory_kanban.py
odoo/addons/stock_request_kanban/models/stock_request.py
odoo/addons/stock_request_kanban/models/stock_request_kanban.py
odoo/addons/stock_request_kanban/readme/CONFIGURE.rst
odoo/addons/stock_request_kanban/readme/CONTRIBUTORS.rst
odoo/addons/stock_request_kanban/readme/DESCRIPTION.rst
odoo/addons/stock_request_kanban/readme/USAGE.rst
odoo/addons/stock_request_kanban/report/report_paper_format.xml
odoo/addons/stock_request_kanban/report/stock_request_kanban_templates.xml
odoo/addons/stock_request_kanban/security/ir.model.access.csv
odoo/addons/stock_request_kanban/static/description/icon.png
odoo/addons/stock_request_kanban/static/description/index.html
odoo/addons/stock_request_kanban/static/src/js/stock_request_kanban_scan_controller.js
odoo/addons/stock_request_kanban/static/src/js/stock_request_kanban_scan_view.js
odoo/addons/stock_request_kanban/static/src/xml/stock_request_kanban_scan.xml
odoo/addons/stock_request_kanban/tests/__init__.py
odoo/addons/stock_request_kanban/tests/base_test.py
odoo/addons/stock_request_kanban/tests/test_inventory_kanban.py
odoo/addons/stock_request_kanban/tests/test_kanban.py
odoo/addons/stock_request_kanban/views/product_views.xml
odoo/addons/stock_request_kanban/views/stock_inventory_kanban_views.xml
odoo/addons/stock_request_kanban/views/stock_request_kanban_views.xml
odoo/addons/stock_request_kanban/views/stock_request_menu.xml
odoo/addons/stock_request_kanban/views/stock_request_order_views.xml
odoo13_addon_stock_request_kanban-13.0.1.0.2.dev7.dist-info/METADATA
odoo13_addon_stock_request_kanban-13.0.1.0.2.dev7.dist-info/WHEEL
odoo13_addon_stock_request_kanban-13.0.1.0.2.dev7.dist-info/top_level.txt
odoo13_addon_stock_request_kanban-13.0.1.0.2.dev7.dist-info/RECORD
